{
  "detected_scale": "1in=16ft",
  "total_area": "15854.2 ft\u00b2",
  "units": "imperial",
  "polygon_vertices": 25,
  "image_size_px": [
    10200,
    6600
  ],
  "footprint_bbox_px": [
    620,
    1436,
    4515,
    5779
  ],
  "px_per_ft": 18.75,
  "walls": [
    {
      "id": "w1",
      "name": "North Wall 1",
      "facing": "North",
      "length": "38.56 ft",
      "length_raw": 38.56,
      "angle_deg": 269.7,
      "px_coords": [
        4511,
        1436,
        3788,
        1440
      ]
    },
    {
      "id": "w2",
      "name": "West Wall 2",
      "facing": "West",
      "length": "79.52 ft",
      "length_raw": 79.52,
      "angle_deg": 180.0,
      "px_coords": [
        3788,
        1440,
        3788,
        2931
      ]
    },
    {
      "id": "w3",
      "name": "North Wall 3",
      "facing": "North",
      "length": "21.33 ft",
      "length_raw": 21.33,
      "angle_deg": 269.9,
      "px_coords": [
        3788,
        2931,
        3388,
        2932
      ]
    },
    {
      "id": "w4",
      "name": "West Wall 4",
      "facing": "West",
      "length": "28.53 ft",
      "length_raw": 28.53,
      "angle_deg": 180.0,
      "px_coords": [
        3388,
        2932,
        3388,
        3467
      ]
    },
    {
      "id": "w5",
      "name": "North Wall 5",
      "facing": "North",
      "length": "6.19 ft",
      "length_raw": 6.19,
      "angle_deg": 267.5,
      "px_coords": [
        3388,
        3467,
        3272,
        3472
      ]
    },
    {
      "id": "w6",
      "name": "West Wall 6",
      "facing": "West",
      "length": "53.21 ft",
      "length_raw": 53.21,
      "angle_deg": 173.3,
      "px_coords": [
        3272,
        3472,
        3388,
        4463
      ]
    },
    {
      "id": "w7",
      "name": "North Wall 7",
      "facing": "North",
      "length": "22.86 ft",
      "length_raw": 22.86,
      "angle_deg": 283.9,
      "px_coords": [
        3388,
        4463,
        2972,
        4360
      ]
    },
    {
      "id": "w8",
      "name": "West Wall 8",
      "facing": "West",
      "length": "5.55 ft",
      "length_raw": 5.55,
      "angle_deg": 180.6,
      "px_coords": [
        2972,
        4360,
        2971,
        4464
      ]
    },
    {
      "id": "w9",
      "name": "North Wall 9",
      "facing": "North",
      "length": "47.52 ft",
      "length_raw": 47.52,
      "angle_deg": 270.0,
      "px_coords": [
        2971,
        4464,
        2080,
        4464
      ]
    },
    {
      "id": "w10",
      "name": "West Wall 10",
      "facing": "West",
      "length": "21.97 ft",
      "length_raw": 21.97,
      "angle_deg": 180.1,
      "px_coords": [
        2080,
        4464,
        2079,
        4876
      ]
    },
    {
      "id": "w11",
      "name": "North Wall 11",
      "facing": "North",
      "length": "77.81 ft",
      "length_raw": 77.81,
      "angle_deg": 270.0,
      "px_coords": [
        2079,
        4876,
        620,
        4876
      ]
    },
    {
      "id": "w12",
      "name": "West Wall 12",
      "facing": "West",
      "length": "38.35 ft",
      "length_raw": 38.35,
      "angle_deg": 180.0,
      "px_coords": [
        620,
        4876,
        620,
        5595
      ]
    },
    {
      "id": "w13",
      "name": "South Wall 13",
      "facing": "South",
      "length": "93.39 ft",
      "length_raw": 93.39,
      "angle_deg": 90.0,
      "px_coords": [
        620,
        5595,
        2371,
        5595
      ]
    },
    {
      "id": "w14",
      "name": "East Wall 14",
      "facing": "East",
      "length": "21.76 ft",
      "length_raw": 21.76,
      "angle_deg": 0.1,
      "px_coords": [
        2371,
        5595,
        2372,
        5187
      ]
    },
    {
      "id": "w15",
      "name": "South Wall 15",
      "facing": "South",
      "length": "68.21 ft",
      "length_raw": 68.21,
      "angle_deg": 90.0,
      "px_coords": [
        2372,
        5187,
        3651,
        5187
      ]
    },
    {
      "id": "w16",
      "name": "West Wall 16",
      "facing": "West",
      "length": "31.57 ft",
      "length_raw": 31.57,
      "angle_deg": 179.9,
      "px_coords": [
        3651,
        5187,
        3652,
        5779
      ]
    },
    {
      "id": "w17",
      "name": "South Wall 17",
      "facing": "South",
      "length": "38.13 ft",
      "length_raw": 38.13,
      "angle_deg": 90.0,
      "px_coords": [
        3652,
        5779,
        4367,
        5779
      ]
    },
    {
      "id": "w18",
      "name": "East Wall 18",
      "facing": "East",
      "length": "60.31 ft",
      "length_raw": 60.31,
      "angle_deg": 4.7,
      "px_coords": [
        4367,
        5779,
        4459,
        4652
      ]
    },
    {
      "id": "w19",
      "name": "North Wall 19",
      "facing": "North",
      "length": "19.63 ft",
      "length_raw": 19.63,
      "angle_deg": 270.2,
      "px_coords": [
        4459,
        4652,
        4091,
        4651
      ]
    },
    {
      "id": "w20",
      "name": "East Wall 20",
      "facing": "East",
      "length": "76.11 ft",
      "length_raw": 76.11,
      "angle_deg": 0.0,
      "px_coords": [
        4091,
        4651,
        4091,
        3224
      ]
    },
    {
      "id": "w21",
      "name": "South Wall 21",
      "facing": "South",
      "length": "10.24 ft",
      "length_raw": 10.24,
      "angle_deg": 89.7,
      "px_coords": [
        4091,
        3224,
        4283,
        3223
      ]
    },
    {
      "id": "w22",
      "name": "West Wall 22",
      "facing": "West",
      "length": "9.73 ft",
      "length_raw": 9.73,
      "angle_deg": 154.0,
      "px_coords": [
        4283,
        3223,
        4363,
        3387
      ]
    },
    {
      "id": "w23",
      "name": "East Wall 23",
      "facing": "East",
      "length": "8.69 ft",
      "length_raw": 8.69,
      "angle_deg": 0.0,
      "px_coords": [
        4363,
        3387,
        4363,
        3224
      ]
    },
    {
      "id": "w24",
      "name": "South Wall 24",
      "facing": "South",
      "length": "8.11 ft",
      "length_raw": 8.11,
      "angle_deg": 88.1,
      "px_coords": [
        4363,
        3224,
        4515,
        3219
      ]
    },
    {
      "id": "w25",
      "name": "East Wall 25",
      "facing": "East",
      "length": "95.09 ft",
      "length_raw": 95.09,
      "angle_deg": 359.9,
      "px_coords": [
        4515,
        3219,
        4511,
        1436
      ]
    }
  ],
  "visualization": "test.annotated.png"
}